data_loading/__init__.py
data_loading-0.0.1.dist-info/METADATA
data_loading-0.0.1.dist-info/WHEEL
data_loading-0.0.1.dist-info/top_level.txt
data_loading-0.0.1.dist-info/RECORD
