Metadata-Version: 2.1
Name: data-loading
Version: 0.0.1
Summary: My first Python package
Author: Xue Wu
Author-email: real_wuxue@yahoo.com
Keywords: python,first package
Classifier: Development Status :: 3 - Alpha
Classifier: Intended Audience :: Education
Classifier: Programming Language :: Python :: 3
Classifier: Topic :: Scientific/Engineering :: Artificial Intelligence
